README.md
setup.py
taobao/__init__.py
taobao/api.py
taobao/comm/__init__.py
taobao/comm/common.py
taobao/exception/__init__.py
taobao/exception/exceptions.py
taobao/model/__init__.py
taobao/model/base.py
taobao/model/trade.py
taobao/model/user.py
taobao/tests/__init__.py
taobao/tests/test_sign.py
taobao/tests/test_trade.py
taobao/tests/test_user.py
taobao/trade/__init__.py
taobao/trade/trade.py
taobao/user/__init__.py
taobao/user/userapi.py
taobao_sdk.egg-info/PKG-INFO
taobao_sdk.egg-info/SOURCES.txt
taobao_sdk.egg-info/dependency_links.txt
taobao_sdk.egg-info/requires.txt
taobao_sdk.egg-info/top_level.txt
taobao_sdk.egg-info/zip-safe